bgm/__init__.py
bgm/__version__.py
bgm/config_default.yaml
bgm/config_processor.py
bgm/environment.py
bgm/environment_flagbased.py
bgm/music_player.py
bgm/music_state_machine.py
bgm/process_service.py
es_bgm-1.2.2.dist-info/entry_points.txt
es_bgm-1.2.2.dist-info/WHEEL
es_bgm-1.2.2.dist-info/METADATA
es_bgm-1.2.2.dist-info/RECORD
