Metadata-Version: 2.1
Name: es-bgm
Version: 1.2.2
Summary: Allows you to add background music to EmulationStation
License: LGPL-3.0-or-later
Author: David
Author-email: davigetto@gmail.com
Requires-Python: >=3.7,<4.0
Classifier: License :: OSI Approved :: GNU Lesser General Public License v3 or later (LGPLv3+)
Classifier: Programming Language :: Python :: 3
Classifier: Programming Language :: Python :: 3.10
Classifier: Programming Language :: Python :: 3.7
Classifier: Programming Language :: Python :: 3.8
Classifier: Programming Language :: Python :: 3.9
Provides-Extra: lint
Requires-Dist: PyYAML (>=6.0,<7.0)
Requires-Dist: confuse (>=1.7.0,<2.0.0)
Requires-Dist: deepmerge (>=1.0.1,<2.0.0)
Requires-Dist: psutil (>=5.9.0,<6.0.0)
Requires-Dist: pydantic (>=1.9.0,<2.0.0)
Requires-Dist: pygame (>=2.0.1,<3.0.0)
Requires-Dist: pylint; extra == "lint"
Requires-Dist: python-decouple (>=3.4,<4.0)
Requires-Dist: transitions (>=0.8.10,<0.9.0)
